{
  "2024": [
    {
      "title": "Lolita",
      "month": 3,
      "ISBN13": 9788845972928
    },
    {
      "title": "Lo stadio di Wimbledon",
      "month": 2,
      "ISBN13": 9788806252397
    },
    {
      "title": "Due vite",
      "month": 2,
      "ISBN13": 9788854522633
    },
    {
      "title": "I fratelli Karamazov",
      "month": 2,
      "ISBN13": 9788811810629
    },
    {
      "title": "Il giuoco delle palle di Vetro",
      "month": 1,
      "ISBN13": 9788804700739
    },
    {
      "title": "Narciso e Boccadoro",
      "month": 1,
      "ISBN13": 9788804668145
    }
  ],
  "2023": [
    {
      "title": "L'atto creativo",
      "month": 12,
      "ISBN13": 9788804756545
    },
    {
      "title": "M. Gli ultimi giorni d'Europa",
      "month": 12,
      "ISBN13": 9788830104969
    },
    {
      "title": "La Montagna Incantata",
      "month": 12,
      "ISBN13": 9788863801682
    },
    {
      "title": "Baudolino",
      "month": 11,
      "ISBN13": 9788834604793
    },
    {
      "title": " Storia dell'umanità per gente che va di fretta",
      "month": 11,
      "ISBN13": 9788842827160
    },
    {
      "title": "Eureka! Storia avventurosa delle scoprte, invenzioni e prime volte che hanno cambiato l'umanità",
      "month": 11,
      "ISBN13": 9788842828860
    },
    {
      "title": "L'avvocato dell'atomo. In difesa dell'energia nucleare",
      "month": 10,
      "ISBN13": 9791259672148
    },
    {
      "title": "il volto del male",
      "month": 10,
      "ISBN13": 9788835725640
    },
    {
      "title": "Il nome della rosa",
      "month": 10,
      "notes": "/books/notes/nome_della_rosa.svg",
      "altNotes": "Ma allora a che serve nascondere i libri se dai libri palesi si può risalire a quelli occulti?",
      "tranlatedNotes": "So, what's the point of hiding books if you can uncover the concealed ones from the evident ones?",
      "ISBN13": 8834603001
    },
    {
      "title": "Una stanza tutta per sé",
      "month": 10,
      "ISBN13": 9788807900600
    },
    {
      "title": "Guerra e pace",
      "month": 10,
      "ISBN13": 9788804682592
    },
    {
      "title": "La donna che rise di Dio",
      "month": 9,
      "ISBN13": 9788831811750
    },
    {
      "title": "La linea verticale", 
      "ISBN13": 9788868528348
    },
    {
      "title": "Marcia su Roma e dintorni", 
      "ISBN13": 9788806221416
    },
    {
      "title": "Un anno sull'altipiano",
      "ISBN13": 9788806219178
    },
    {
      "title": "Poiana e i suoi fratelli",
      "ISBN13": 9788832089547
    },
    {
      "title": "Mussolini il Capobanda",
      "ISBN13": 9788804751168
    },
    {
      "title": "Vent'anni dopo",
      "ISBN13": 9788804488019
    },
    {
      "title": "L'ingegno e la tenebre",
      "ISBN13": 9788817161718
    },
    {
      "title": "...che Dio perdona a tutti",
      "ISBN13": 9788807893056
    },
    {
      "title": "Se una notte d'inverno un viaggiatore",
      "ISBN13": 9788481304473
    },
    {
      "title": "M. l'Uomo della Provvidenza",
      
      
      "ISBN13": 9788830102651
    },
    {
      "title": "Un ottimista in America",
      "ISBN13": 9788804644873
    },
    {
      "title": "Musicophilia: Tales of Music and the Brain",
      "ISBN13": 9780330523592
    },
    {
      "title": "Il mito di Sisifo",
      "ISBN13": 9788845246425
    },
    {
      "title": "I tacchini non ringraziano",
      "ISBN13": 9788893816151
    },
    {
      "title": "Il cavaliere inesistente",
      "ISBN13": 9788804772712
    },
    {
      "title": "Il conte di Montecristo",
      "ISBN13": 9788807901157
    },
    {
      "title": "Ba-da-bum!",
      "ISBN13": 9788807881787
    },
    {
      "title": "M. Il figlio del secolo",
      "ISBN13": 9788830106628
    },
    {
      "title": "Il gattopardo",
      "ISBN13": 9788858808832
    },
    {
      "title": "In mezzo al mare. Sette atti comici",
      "ISBN13": 9788804736714
    },
    {
      "title": "Perché comincio dalla fine",
      "ISBN13": 9788829701766
    },
    {
      "title": "Moby Dick",
      "ISBN13": 9788807900761
    },
    {
      "title": "Il visconte dimezzato",
      "ISBN13": 9788804776369
    },
    {
      "title": "Delitto e castigo",
      "ISBN13": 9788806220457
    },
    {
      "title": "Memoriale dal convento",
      "ISBN13": 9788807889349
    },
    {
      "title": "Marcovaldo",
      "ISBN13": 9788804776383
    },
    {
      "title": "La valle dell'eden",
      "ISBN13": 9788845274060
    },
    {
      "title": "La chiave",
      "ISBN13": 9788845283017
    },
    {
      "title": "Le piccole virtù",
      "ISBN13": 9788806225735
    },
    {
      "title": "Il vangelo secondo Gesù Cristo",
      "ISBN13": 9788807885341
    },
    {
      "title": "Uomini e topi",
      "ISBN13": 9788845282980
    },
    {
      "title": "Orgoglio e pregiudizio",
      "ISBN13": 9788807900846
    },
    {
      "title": "La noia",
      "ISBN13": 9788845283970
    },
    {
      "title": "Cecità",
      "ISBN13": 9788807881572
    },
    {
      "title": "California: La fine del sogno",
      "ISBN13": 9788804755210
    }
  ],
  "2022": [
    {
      "title": "Lo straniero",
      "ISBN13": 9788845277634
    },
    {
      "title": "La peste",
      "ISBN13": 9782701161662
    },
    {
      "title": "Storia perfetta dell'errore",
      "ISBN13": 9788817143509
    },
    {
      "title": "Bomba atomica",
      "ISBN13": 9788817147347
    },
    {
      "title": "La società della performance",
      "ISBN13": 9788899684501
    },
    {
      "title": "Guerre ed eserciti nel Medioevo",
      "ISBN13": 9788815279569
    }
  ],
  "2021": [
    {
      "title": "Le città invisibili",
      "ISBN13": 9788806476397
    },
    {
      "title": "Madame Bovary",
      "ISBN13": 9788807900983
    },
    {
      "title": "Le mie risposte alle grandi domande",
      "ISBN13": 9788817105279
    },
    {
      "title": "Una storia americana",
      "ISBN13": 9788804739746
    },
    {
      "title": "Questa è l'America",
      "ISBN13": 9788804734338
    },
    {
      "title": "Of Ants and Dinosaurs",
      "ISBN13": 9781789546125
    },
    {
      "title": "21 lezioni per il XXI secolo",
      "ISBN13": 9788830100824
    },
    {
      "title": "Homo Deus. Breve storia del futuro",
      "ISBN13": 9788845298752
    }
  ],
  "2020": [
    {
      "title": "Sapiens. Da animali a dèi: breve storia dell'umanità",
      "ISBN13": 9788845296499
    }
  ],
  "🤷": [

  ]
}
